medviz/__init__.py
medviz/ct_local/__init__.py
medviz/ct_local/hist.py
medviz/ct_local/metadata_local.py
medviz/feats/__init__.py
medviz/feats/collage/__init__.py
medviz/feats/collage/collage2d.py
medviz/feats/collage/collage3d.py
medviz/feats/collage/compute_collage.py
medviz/feats/collage/main.py
medviz/feats/collage/stats.py
medviz/multimodal/__init__.py
medviz/multimodal/save_dicom_metadata.py
medviz/multimodal/stats.py
medviz/plot/__init__.py
medviz/plot/gif.py
medviz/plot/plot3d.py
medviz/plot/plot_helpers.py
medviz/preprocess/__init__.py
medviz/preprocess/hu.py
medviz/preprocess/mask.py
medviz/preprocess/match_image_mask.py
medviz/preprocess/meta_helpers.py
medviz/preprocess/metadata.py
medviz/preprocess/resampling.py
medviz/preprocess/resampling_local.py
medviz/preprocess/resampling_local_stik.py
medviz/preprocess/series2whole.py
medviz/preprocess/transformation_local_.py
medviz/utils/__init__.py
medviz/utils/array_profile.py
medviz/utils/array_threshold.py
medviz/utils/custom_type.py
medviz/utils/helper_mask.py
medviz/utils/helper_path.py
medviz/utils/helper_reader.py
medviz/utils/helper_reader_local.py
medviz/utils/log.py
medviz/utils/utility.py
medviz-1.2.0.dist-info/LICENSE
medviz-1.2.0.dist-info/METADATA
medviz-1.2.0.dist-info/WHEEL
medviz-1.2.0.dist-info/top_level.txt
medviz-1.2.0.dist-info/RECORD
