Metadata-Version: 2.1
Name: medviz
Version: 1.2.0
Summary: Medical Image Visualization Tool 🐍🚀🎉🦕
Author-email: Mohsen Hariri <mohsen.hariri@case.eud>
License: GPL-3.0 License
Keywords: MRI,CT
Classifier: Programming Language :: Python :: 3.8
Classifier: License :: OSI Approved :: GNU General Public License v3 or later (GPLv3+)
Classifier: Operating System :: OS Independent
Requires-Python: >=3.6
License-File: LICENSE
Requires-Dist: numpy >=1.19.5
Requires-Dist: pandas >=1.2.4
Requires-Dist: matplotlib >=3.3.4
Requires-Dist: nibabel >=3.2.1
Requires-Dist: imageio >=2.9.0
Requires-Dist: scikit-image >=0.18.3
Requires-Dist: tabulate >=0.8.9
Requires-Dist: pydicom >=2.1.2
Requires-Dist: SimpleITK >=2.1.1
Requires-Dist: mahotas >=1.4.11
Requires-Dist: importlib-metadata ; python_version < "3.8"
